single_table_orm/__init__.py
single_table_orm/connection.py
single_table_orm/fields.py
single_table_orm/model_jsonata.py
single_table_orm/models.py
single_table_orm/table_definition.py
single_table_orm-0.2.2.dist-info/licenses/LICENSE
single_table_orm-0.2.2.dist-info/METADATA
single_table_orm-0.2.2.dist-info/WHEEL
single_table_orm-0.2.2.dist-info/top_level.txt
single_table_orm-0.2.2.dist-info/RECORD
