Metadata-Version: 2.4
Name: single-table-orm
Version: 0.2.2
Summary: A Django-like ORM for AWS DynamoDB using single-table design.
Author: Stijn De Pauw
License: MIT License
Classifier: Programming Language :: Python :: 3
Classifier: License :: OSI Approved :: MIT License
Classifier: Operating System :: OS Independent
Classifier: Intended Audience :: Developers
Classifier: Topic :: Database
Classifier: Topic :: Software Development :: Libraries :: Python Modules
Requires-Python: >=3.7
License-File: LICENSE
Requires-Dist: boto3
Requires-Dist: jsonata-python
Requires-Dist: boto3-stubs[dynamodb]
Requires-Dist: pydantic
Dynamic: license-file
